email_client/__init__.py
email_client/client.py
email_client/utils.py
email_client-1.5.2.dist-info/METADATA
email_client-1.5.2.dist-info/WHEEL
email_client-1.5.2.dist-info/top_level.txt
email_client-1.5.2.dist-info/RECORD
