Metadata-Version: 2.1
Name: email-client
Version: 1.5.2
Summary: Email clients for grader and other services of fless.pro
Home-page: https://github.com/Flesspro/email-client
Author: Egor Urvanov
Author-email: hedgehogues@bk.ru
License: UNKNOWN
Platform: UNKNOWN
Classifier: Programming Language :: Python :: 3.7
Classifier: Operating System :: OS Independent
Requires-Dist: table-test (>=0.4.2)
Requires-Dist: requests (>=2.24.0)
Requires-Dist: pytest (>=6.0.1)
Requires-Dist: python-dotenv (>=0.14.0)
